torchopviz/__init__.py
torchopviz/comm.py
torchopviz/complex_graph.py
torchopviz/launch_server.py
torchopviz/log.py
torchopviz/memory_profile.py
torchopviz/offline_viz.py
torchopviz/online_viz.py
torchopviz/utils.py
torchopviz/server/static/js/visualizer.js
torchopviz/server/templates/index.html
torchopviz-0.1.1.dist-info/licenses/LICENSE
torchopviz-0.1.1.dist-info/METADATA
torchopviz-0.1.1.dist-info/WHEEL
torchopviz-0.1.1.dist-info/top_level.txt
torchopviz-0.1.1.dist-info/RECORD
