Metadata-Version: 2.4
Name: torchopviz
Version: 0.1.1
Summary: A small package to create visualizations of PyTorch operation execution
Author-email: cjj535 <767876863@qq.com>
License: MIT
Project-URL: Homepage, https://github.com/cjj535/torchopviz
Project-URL: Repository, https://github.com/cjj535/torchopviz
Classifier: Programming Language :: Python :: 3
Classifier: License :: OSI Approved :: MIT License
Classifier: Operating System :: OS Independent
Requires-Python: >=3.9
License-File: LICENSE
Requires-Dist: flask==3.1.2
Requires-Dist: graphviz==0.21
Dynamic: license-file
